[
  {
    "name": "Turretus Enemies",
    "sections": [ { "name": "Turretus" } ],
    "map_locations": [
      { "map": "Dragon Valley (Image 1)", "x": 2436, "y": 1381 },
      { "map": "Dragon Valley (Image 1)", "x": 2913, "y": 985 },
      { "map": "Dragon Valley (Image 1)", "x": 3676, "y": 1074 },
      { "map": "Dragon Valley (Image 2)", "x": 79, "y": 1472 },
      { "map": "Dragon Valley (Image 2)", "x": 542, "y": 1586 },
      { "map": "Dragon Valley (Image 2)", "x": 791, "y": 1046 },
      { "map": "Dragon Valley (Image 2)", "x": 2146, "y": 1156 },
      { "map": "Dragon Valley (Image 3)", "x": 1649, "y": 1075 },
      { "map": "Dragon Valley (Image 3)", "x": 3013, "y": 391 },
      { "map": "Dragon Valley (Image 3)", "x": 3195, "y": 465 },
      { "map": "Dragon Valley (Image 4)", "x": 2289, "y": 1454 },
      { "map": "Dragon Valley (Image 5)", "x": 805, "y": 1844 },
      { "map": "Dragon Valley (Image 5)", "x": 1435, "y": 479 },
      { "map": "Dragon Valley (Image 6)", "x": 2094, "y": 776 },
      { "map": "Dragon Valley (Image 6)", "x": 2118, "y": 394 },
      { "map": "Dragon Valley (Image 7)", "x": 72, "y": 417 },
      { "map": "Dragon Valley (Image 7)", "x": 592, "y": 767 },
      { "map": "Dragon Valley (Image 7)", "x": 1012, "y": 366 },
      { "map": "Dragon Valley (Image 8)", "x": 1370, "y": 1296 },
      { "map": "Dragon Valley (Image 8)", "x": 1558, "y": 1243 },
      { "map": "Dragon Valley (Image 10)", "x": 342, "y": 1334 },
      { "map": "Dragon Valley (Image 10)", "x": 452, "y": 1239 },
      { "map": "Robot Graveyard (Image 1)", "x": 1160, "y": 979 },
      { "map": "Robot Graveyard (Image 1)", "x": 2373, "y": 955 },
      { "map": "Robot Graveyard (Image 1)", "x": 2637, "y": 1667 },
      { "map": "Robot Graveyard (Image 1)", "x": 2813, "y": 1677 },
      { "map": "Robot Graveyard (Image 1)", "x": 2899, "y": 1024 },
      { "map": "Robot Graveyard (Image 1)", "x": 3531, "y": 1268 },
      { "map": "Robot Graveyard (Image 1)", "x": 3689, "y": 1323 },
      { "map": "Robot Graveyard (Image 2)", "x": 944, "y": 1661 },
      { "map": "Robot Graveyard (Image 2)", "x": 1047, "y": 1532 },
      { "map": "Robot Graveyard (Image 2)", "x": 1120, "y": 1616 },
      { "map": "Robot Graveyard (Image 2)", "x": 1434, "y": 1046 },
      { "map": "Robot Graveyard (Image 2)", "x": 1869, "y": 1119 },
      { "map": "Robot Graveyard (Image 2)", "x": 2438, "y": 1122 }
    ]
  },
  {
    "name": "Spy Turretus Enemies",
    "sections": [ { "name": "Spy Turretus" } ],
    "map_locations": [
      { "map": "Dragon Valley (Image 1)", "x": 3429, "y": 1077 },
      { "map": "Dragon Valley (Image 1)", "x": 3472, "y": 1363 },
      { "map": "Dragon Valley (Image 2)", "x": 247, "y": 1125 },
      { "map": "Dragon Valley (Image 2)", "x": 1077, "y": 1005 },
      { "map": "Dragon Valley (Image 2)", "x": 2389, "y": 905 },
      { "map": "Dragon Valley (Image 3)", "x": 2232, "y": 976 },
      { "map": "Dragon Valley (Image 3)", "x": 3673, "y": 451 },
      { "map": "Dragon Valley (Image 3)", "x": 3677, "y": 715 },
      { "map": "Dragon Valley (Image 4)", "x": 2004, "y": 742 },
      { "map": "Dragon Valley (Image 5)", "x": 3136, "y": 604 },
      { "map": "Dragon Valley (Image 5)", "x": 3150, "y": 872 },
      { "map": "Dragon Valley (Image 6)", "x": 182, "y": 1173 },
      { "map": "Dragon Valley (Image 6)", "x": 316, "y": 614 },
      { "map": "Dragon Valley (Image 6)", "x": 1327, "y": 886 },
      { "map": "Dragon Valley (Image 6)", "x": 1494, "y": 385 },
      { "map": "Dragon Valley (Image 7)", "x": 217, "y": 710 },
      { "map": "Dragon Valley (Image 7)", "x": 1157, "y": 266 },
      { "map": "Dragon Valley (Image 7)", "x": 1667, "y": 309 },
      { "map": "Dragon Valley (Image 7)", "x": 2054, "y": 1082 },
      { "map": "Dragon Valley (Image 7)", "x": 2660, "y": 724 },
      { "map": "Dragon Valley (Image 8)", "x": 1367, "y": 1053 },
      { "map": "Dragon Valley (Image 10)", "x": 166, "y": 1387 },
      { "map": "Dragon Valley (Image 10)", "x": 453, "y": 1540 },
      { "map": "Robot Graveyard (Image 1)", "x": 1315, "y": 965 },
      { "map": "Robot Graveyard (Image 1)", "x": 1569, "y": 1342 },
      { "map": "Robot Graveyard (Image 1)", "x": 1682, "y": 1244 },
      { "map": "Robot Graveyard (Image 1)", "x": 1789, "y": 965 },
      { "map": "Robot Graveyard (Image 1)", "x": 1843, "y": 1475 },
      { "map": "Robot Graveyard (Image 1)", "x": 1909, "y": 1058 },
      { "map": "Robot Graveyard (Image 1)", "x": 1960, "y": 1944 },
      { "map": "Robot Graveyard (Image 1)", "x": 1976, "y": 1184 },
      { "map": "Robot Graveyard (Image 1)", "x": 2349, "y": 1312 },
      { "map": "Robot Graveyard (Image 1)", "x": 2424, "y": 1833 },
      { "map": "Robot Graveyard (Image 1)", "x": 2529, "y": 1356 },
      { "map": "Robot Graveyard (Image 1)", "x": 2571, "y": 1908 },
      { "map": "Robot Graveyard (Image 1)", "x": 2603, "y": 903 },
      { "map": "Robot Graveyard (Image 1)", "x": 2904, "y": 1153 },
      { "map": "Robot Graveyard (Image 2)", "x": 299, "y": 1673 },
      { "map": "Robot Graveyard (Image 2)", "x": 1435, "y": 1212 },
      { "map": "Robot Graveyard (Image 2)", "x": 1800, "y": 1095 },
      { "map": "Robot Graveyard (Image 2)", "x": 2721, "y": 634 },
      { "map": "Shade Armory (Image 1)", "x": 1756, "y": 893 },
      { "map": "Shade Armory (Image 1)", "x": 1850, "y": 688 },
      { "map": "Shade Armory (Image 1)", "x": 2548, "y": 1062 },
      { "map": "Shade Armory (Image 1)", "x": 2811, "y": 1696 },
      { "map": "Shade Armory (Image 1)", "x": 2918, "y": 1612 },
      { "map": "Shade Armory (Image 1)", "x": 3029, "y": 1738 },
      { "map": "Shade Armory (Image 1)", "x": 3212, "y": 1368 },
      { "map": "Shade Armory (Image 1)", "x": 3255, "y": 1257 },
      { "map": "Shade Armory (Image 1)", "x": 3392, "y": 1750 },
      { "map": "Shade Armory (Image 2)", "x": 162, "y": 1662 },
      { "map": "Shade Armory (Image 2)", "x": 299, "y": 1754 },
      { "map": "Shade Armory (Image 2)", "x": 529, "y": 1342 },
      { "map": "Shade Armory (Image 2)", "x": 576, "y": 1517 },
      { "map": "Shade Armory (Image 2)", "x": 1744, "y": 1549 },
      { "map": "Shade Armory (Image 2)", "x": 1823, "y": 1141 },
      { "map": "Shade Armory (Image 2)", "x": 2173, "y": 1536 },
      { "map": "Shade Armory (Image 2)", "x": 2313, "y": 913 },
      { "map": "Shade Armory (Image 2)", "x": 2476, "y": 945 },
      { "map": "Shade Armory (Image 2)", "x": 2649, "y": 907 },
      { "map": "Shade Armory (Image 2)", "x": 2930, "y": 855 }
    ]
  },
  {
    "name": "Line Cutter Enemies",
    "sections": [ { "name": "Line Cutter" } ],
    "map_locations": [
      { "map": "Dragon Valley (Image 2)", "x": 1349, "y": 1429 },
      { "map": "Dragon Valley (Image 2)", "x": 3329, "y": 818 },
      { "map": "Dragon Valley (Image 2)", "x": 3455, "y": 1009 },
      { "map": "Dragon Valley (Image 2)", "x": 3664, "y": 1803 },
      { "map": "Dragon Valley (Image 2)", "x": 3825, "y": 1607 },
      { "map": "Dragon Valley (Image 3)", "x": 76, "y": 1803 },
      { "map": "Dragon Valley (Image 3)", "x": 519, "y": 1521 },
      { "map": "Dragon Valley (Image 3)", "x": 1996, "y": 1817 },
      { "map": "Dragon Valley (Image 3)", "x": 2132, "y": 1322 },
      { "map": "Dragon Valley (Image 5)", "x": 2009, "y": 1485 },
      { "map": "Dragon Valley (Image 5)", "x": 2565, "y": 1020 },
      { "map": "Dragon Valley (Image 5)", "x": 2731, "y": 1220 },
      { "map": "Dragon Valley (Image 5)", "x": 2816, "y": 1020 },
      { "map": "Dragon Valley (Image 5)", "x": 2980, "y": 1220 },
      { "map": "Dragon Valley (Image 7)", "x": 3375, "y": 1231 },
      { "map": "Dragon Valley (Image 7)", "x": 3604, "y": 1378 },
      { "map": "Dragon Valley (Image 8)", "x": 670, "y": 1106 },
      { "map": "Dragon Valley (Image 8)", "x": 818, "y": 993 },
      { "map": "Dragon Valley (Image 8)", "x": 880, "y": 1064 },
      { "map": "Dragon Valley (Image 8)", "x": 1042, "y": 962 },
      { "map": "Dragon Valley (Image 8)", "x": 1105, "y": 953 },
      { "map": "Dragon Valley (Image 8)", "x": 1529, "y": 799 }
    ]
  },
  {
    "name": "Drake Fly Enemies",
    "sections": [ { "name": "Drake Fly" } ],
    "map_locations": [
      { "map": "Dragon Valley (Image 2)", "x": 2102, "y": 913 },
      { "map": "Dragon Valley (Image 3)", "x": 1389, "y": 1824 },
      { "map": "Dragon Valley (Image 4)", "x": 832, "y": 1486 },
      { "map": "Dragon Valley (Image 5)", "x": 544, "y": 1568 },
      { "map": "Dragon Valley (Image 5)", "x": 686, "y": 1807 },
      { "map": "Dragon Valley (Image 5)", "x": 1030, "y": 866 },
      { "map": "Dragon Valley (Image 5)", "x": 1320, "y": 441 },
      { "map": "Dragon Valley (Image 5)", "x": 3238, "y": 1123 },
      { "map": "Dragon Valley (Image 6)", "x": 280, "y": 1605 },
      { "map": "Dragon Valley (Image 6)", "x": 2185, "y": 727 }
    ]
  },
  {
    "name": "Keon Enemies",
    "sections": [ { "name": "Keon" } ],
    "map_locations": [
      { "map": "Dragon Valley (Image 4)", "x": 3449, "y": 1167 },
      { "map": "Dragon Valley (Image 4)", "x": 3711, "y": 1169 },
      { "map": "Dragon Valley (Image 4)", "x": 3769, "y": 1509 },
      { "map": "Dragon Valley (Image 5)", "x": 363, "y": 1170 },
      { "map": "Dragon Valley (Image 5)", "x": 554, "y": 937 },
      { "map": "Dragon Valley (Image 5)", "x": 3717, "y": 1105 },
      { "map": "Dragon Valley (Image 6)", "x": 416, "y": 1705 },
      { "map": "Dragon Valley (Image 6)", "x": 1118, "y": 1361 },
      { "map": "Dragon Valley (Image 6)", "x": 1530, "y": 1180 },
      { "map": "Dragon Valley (Image 6)", "x": 1829, "y": 1094 },
      { "map": "Dragon Valley (Image 8)", "x": 1368, "y": 1399 },
      { "map": "Dragon Valley (Image 8)", "x": 1892, "y": 1247 }
    ]
  },
  {
    "name": "Meteor Roller Enemies",
    "sections": [ { "name": "Meteor Roller" } ],
    "map_locations": [
      { "map": "Shenlin Park (Image 1)", "x": 1459, "y": 1215 },
      { "map": "Shenlin Park (Image 1)", "x": 1687, "y": 1215 },
      { "map": "Shenlin Park (Image 1)", "x": 2100, "y": 1130 },
      { "map": "Shenlin Park (Image 1)", "x": 2355, "y": 1130 },
      { "map": "Shenlin Park (Image 1)", "x": 2512, "y": 1043 },
      { "map": "Shenlin Park (Image 1)", "x": 2648, "y": 869 },
      { "map": "Shenlin Park (Image 1)", "x": 2757, "y": 869 },
      { "map": "Shenlin Park (Image 1)", "x": 2876, "y": 1130 },
      { "map": "Shenlin Park (Image 1)", "x": 3506, "y": 1304 },
      { "map": "Shenlin Park (Image 1)", "x": 3707, "y": 1199 },
      { "map": "Shenlin Park (Image 2)", "x": 2011, "y": 1065 },
      { "map": "Shenlin Park (Image 2)", "x": 2004, "y": 1499 },
      { "map": "Shenlin Park (Image 3)", "x": 2635, "y": 1064 },
      { "map": "Shenlin Park (Image 3)", "x": 2788, "y": 890 },
      { "map": "Shenlin Park (Image 3)", "x": 3191, "y": 1326 },
      { "map": "Shenlin Park (Image 3)", "x": 3548, "y": 1152 },
      { "map": "Shenlin Park (Image 4)", "x": 66, "y": 1065 },
      { "map": "Shenlin Park (Image 4)", "x": 1998, "y": 1172 },
      { "map": "Shenlin Park (Image 4)", "x": 2113, "y": 1216 },
      { "map": "Shenlin Park (Image 4)", "x": 2575, "y": 1172 },
      { "map": "Shenlin Park (Image 5)", "x": 2778, "y": 1652 },
      { "map": "Shenlin Park (Image 6)", "x": 304, "y": 1304 },
      { "map": "Shenlin Park (Image 6)", "x": 1265, "y": 1173 },
      { "map": "Shenlin Park (Image 6)", "x": 1478, "y": 1173 },
      { "map": "Shenlin Park (Image 6)", "x": 1857, "y": 544 },
      { "map": "Shenlin Park (Image 7)", "x": 3162, "y": 968 },
      { "map": "Shenlin Park (Image 7)", "x": 3316, "y": 1087 },
      { "map": "Shenlin Park (Image 10)", "x": 1774, "y": 673 },
      { "map": "Shenlin Park (Image 10)", "x": 2123, "y": 673 },
      { "map": "Shenlin Park (Image 10)", "x": 2252, "y": 1022 },
      { "map": "Shenlin Park (Image 10)", "x": 2429, "y": 1162 },
      { "map": "Shenlin Park (Image 10)", "x": 2513, "y": 971 },
      { "map": "Shenlin Park (Image 10)", "x": 2508, "y": 1347 },
      { "map": "Shenlin Park (Image 10)", "x": 2562, "y": 1128 },
      { "map": "Shenlin Park (Image 10)", "x": 2758, "y": 1113 },
      { "map": "Shenlin Park (Image 10)", "x": 2773, "y": 972 },
      { "map": "Shenlin Park (Image 10)", "x": 2773, "y": 1345 },
      { "map": "Shenlin Park (Image 10)", "x": 2816, "y": 1415 },
      { "map": "Shenlin Park (Image 10)", "x": 2860, "y": 819 },
      { "map": "Shenlin Park (Image 10)", "x": 2953, "y": 1415 },
      { "map": "Shenlin Park (Image 10)", "x": 3040, "y": 1021 },
      { "map": "Shenlin Park (Image 10)", "x": 3121, "y": 1021 }
    ]
  },
  {
    "name": "Peller Enemies",
    "sections": [ { "name": "Peller" } ],
    "map_locations": [
      { "map": "Shenlin Park (Image 2)", "x": 137, "y": 1099 },
      { "map": "Shenlin Park (Image 2)", "x": 918, "y": 1147 },
      { "map": "Shenlin Park (Image 2)", "x": 1738, "y": 1050 },
      { "map": "Shenlin Park (Image 2)", "x": 1901, "y": 1088 },
      { "map": "Shenlin Park (Image 2)", "x": 2551, "y": 1284 },
      { "map": "Shenlin Park (Image 2)", "x": 3185, "y": 931 },
      { "map": "Shenlin Park (Image 4)", "x": 1110, "y": 1061 },
      { "map": "Shenlin Park (Image 4)", "x": 1710, "y": 540 },
      { "map": "Shenlin Park (Image 4)", "x": 2345, "y": 697 },
      { "map": "Shenlin Park (Image 6)", "x": 1574, "y": 1083 },
      { "map": "Shenlin Park (Image 6)", "x": 2947, "y": 860 },
      { "map": "Shenlin Park (Image 9)", "x": 1917, "y": 659 },
      { "map": "Shenlin Park (Image 10)", "x": 2208, "y": 936 },
      { "map": "Shenlin Park (Image 10)", "x": 2354, "y": 1322 },
      { "map": "Shenlin Park (Image 10)", "x": 3098, "y": 1288 }
    ]
  },
  {
    "name": "Traumagotcha Enemies",
    "sections": [ { "name": "Traumagotcha" } ],
    "map_locations": [
      { "map": "Shenlin Park (Image 2)", "x": 3665, "y": 1080 },
      { "map": "Shenlin Park (Image 3)", "x": 2550, "y": 819 },
      { "map": "Shenlin Park (Image 4)", "x": 1472, "y": 575 },
      { "map": "Shenlin Park (Image 5)", "x": 373, "y": 1432 },
      { "map": "Shenlin Park (Image 5)", "x": 3549, "y": 1563 },
      { "map": "Shenlin Park (Image 7)", "x": 2191, "y": 1064 },
      { "map": "Shenlin Park (Image 9)", "x": 465, "y": 1281 },
      { "map": "Shenlin Park (Image 10)", "x": 3006, "y": 943 },
      { "map": "Shenlin Park (Image 12)", "x": 1151, "y": 922 }
    ]
  },
  {
    "name": "Pendurum Enemies",
    "sections": [ { "name": "Pendurum" } ],
    "map_locations": [
      { "map": "Shenlin Park (Image 5)", "x": 2911, "y": 784 },
      { "map": "Shenlin Park (Image 6)", "x": 1020, "y": 1332 },
      { "map": "Shenlin Park (Image 6)", "x": 1237, "y": 680 },
      { "map": "Shenlin Park (Image 7)", "x": 2574, "y": 746 },
      { "map": "Shenlin Park (Image 7)", "x": 3399, "y": 930 },
      { "map": "Shenlin Park (Image 8)", "x": 1014, "y": 1619 },
      { "map": "Shenlin Park (Image 8)", "x": 2018, "y": 1760 },
      { "map": "Shenlin Park (Image 8)", "x": 2734, "y": 1516 },
      { "map": "Shenlin Park (Image 9)", "x": 3247, "y": 702 }
    ]
  },
  {
    "name": "Jawdrop Enemies",
    "sections": [ { "name": "Jawdrop" } ],
    "map_locations": [
      { "map": "Shenlin Park (Image 6)", "x": 3608, "y": 612 },
      { "map": "Shenlin Park (Image 7)", "x": 1087, "y": 954 },
      { "map": "Shenlin Park (Image 7)", "x": 3057, "y": 503 },
      { "map": "Shenlin Park (Image 8)", "x": 1188, "y": 742 },
      { "map": "Shenlin Park (Image 8)", "x": 2696, "y": 1230 },
      { "map": "Shenlin Park (Image 8)", "x": 3005, "y": 1344 },
      { "map": "Shenlin Park (Image 8)", "x": 3158, "y": 1290 },
      { "map": "Shenlin Park (Image 8)", "x": 3445, "y": 1257 },
      { "map": "Shenlin Park (Image 9)", "x": 1087, "y": 1171 },
      { "map": "Shenlin Park (Image 9)", "x": 2102, "y": 633 },
      { "map": "Shenlin Park (Image 11)", "x": 538, "y": 1034 },
      { "map": "Shenlin Park (Image 11)", "x": 1341, "y": 986 },
      { "map": "Shenlin Park (Image 11)", "x": 1689, "y": 926 }
    ]
  },
  {
    "name": "Tower Cannon Enemies",
    "sections": [ { "name": "Tower Cannon" } ],
    "map_locations": [
      { "map": "Shenlin Park (Image 11)", "x": 126, "y": 1252 },
      { "map": "Shenlin Park (Image 11)", "x": 735, "y": 1090 },
      { "map": "Shenlin Park (Image 11)", "x": 1479, "y": 1150 },
      { "map": "Shenlin Park (Image 11)", "x": 1864, "y": 1253 },
      { "map": "Shenlin Park (Image 12)", "x": 195, "y": 1086 },
      { "map": "Shenlin Park (Image 12)", "x": 1063, "y": 1291 },
      { "map": "Shenlin Park (Image 12)", "x": 1063, "y": 1357 },
      { "map": "Shenlin Park (Image 12)", "x": 1888, "y": 1014 },
      { "map": "Shenlin Park (Image 12)", "x": 1888, "y": 1079 },
      { "map": "Shenlin Park (Image 12)", "x": 2713, "y": 1020 },
      { "map": "Shenlin Park (Image 12)", "x": 2713, "y": 1086 },
      { "map": "Shenlin Park (Image 12)", "x": 2713, "y": 1150 }
    ]
  },
  {
    "name": "Beartle Enemies",
    "sections": [ { "name": "Beartle" } ],
    "map_locations": [
      { "map": "Tiger Falls (Image 1)", "x": 1266, "y": 1504 },
      { "map": "Tiger Falls (Image 1)", "x": 2591, "y": 411 },
      { "map": "Tiger Falls (Image 1)", "x": 3229, "y": 519 },
      { "map": "Tiger Falls (Image 2)", "x": 313, "y": 936 },
      { "map": "Tiger Falls (Image 2)", "x": 523, "y": 973 },
      { "map": "Tiger Falls (Image 2)", "x": 545, "y": 1001 },
      { "map": "Tiger Falls (Image 2)", "x": 716, "y": 677 },
      { "map": "Tiger Falls (Image 2)", "x": 731, "y": 1346 },
      { "map": "Tiger Falls (Image 2)", "x": 2453, "y": 307 },
      { "map": "Tiger Falls (Image 2)", "x": 3324, "y": 384 },
      { "map": "Tiger Falls (Image 3)", "x": 452, "y": 1114 },
      { "map": "Tiger Falls (Image 3)", "x": 1941, "y": 607 },
      { "map": "Tiger Falls (Image 3)", "x": 2027, "y": 973 },
      { "map": "Tiger Falls (Image 3)", "x": 2093, "y": 844 }
    ]
  },
  {
    "name": "Koi Cannon Enemies",
    "sections": [ { "name": "Koi Cannon" } ],
    "map_locations": [
      { "map": "Tiger Falls (Image 1)", "x": 1389, "y": 1707 },
      { "map": "Tiger Falls (Image 1)", "x": 1483, "y": 1741 },
      { "map": "Tiger Falls (Image 1)", "x": 1579, "y": 1815 },
      { "map": "Tiger Falls (Image 1)", "x": 1656, "y": 1839 },
      { "map": "Tiger Falls (Image 1)", "x": 1997, "y": 1272 },
      { "map": "Tiger Falls (Image 1)", "x": 2058, "y": 1243 },
      { "map": "Tiger Falls (Image 1)", "x": 2124, "y": 1217 },
      { "map": "Tiger Falls (Image 1)", "x": 2359, "y": 1094 },
      { "map": "Tiger Falls (Image 1)", "x": 2414, "y": 1094 },
      { "map": "Tiger Falls (Image 1)", "x": 3407, "y": 585 },
      { "map": "Tiger Falls (Image 2)", "x": 700, "y": 1393 },
      { "map": "Tiger Falls (Image 2)", "x": 904, "y": 1514 },
      { "map": "Tiger Falls (Image 2)", "x": 1034, "y": 1619 },
      { "map": "Tiger Falls (Image 2)", "x": 1081, "y": 1577 },
      { "map": "Tiger Falls (Image 2)", "x": 1145, "y": 1607 },
      { "map": "Tiger Falls (Image 2)", "x": 1176, "y": 1650 },
      { "map": "Tiger Falls (Image 2)", "x": 2268, "y": 815 },
      { "map": "Tiger Falls (Image 2)", "x": 2335, "y": 887 },
      { "map": "Tiger Falls (Image 2)", "x": 2608, "y": 795 },
      { "map": "Tiger Falls (Image 2)", "x": 2904, "y": 719 },
      { "map": "Tiger Falls (Image 2)", "x": 2982, "y": 949 },
      { "map": "Tiger Falls (Image 2)", "x": 3091, "y": 1009 },
      { "map": "Tiger Falls (Image 2)", "x": 3111, "y": 665 },
      { "map": "Tiger Falls (Image 2)", "x": 3273, "y": 1021 },
      { "map": "Tiger Falls (Image 2)", "x": 3321, "y": 602 },
      { "map": "Tiger Falls (Image 2)", "x": 3364, "y": 600 },
      { "map": "Tiger Falls (Image 2)", "x": 3414, "y": 1062 },
      { "map": "Tiger Falls (Image 2)", "x": 3460, "y": 576 },
      { "map": "Tiger Falls (Image 2)", "x": 3534, "y": 554 },
      { "map": "Tiger Falls (Image 3)", "x": 2672, "y": 1327 },
      { "map": "Tiger Falls (Image 3)", "x": 2847, "y": 1308 },
      { "map": "Tiger Falls (Image 3)", "x": 3038, "y": 1271 },
      { "map": "Tiger Falls (Image 3)", "x": 3220, "y": 1241 },
      { "map": "Tiger Falls (Image 3)", "x": 3570, "y": 1152 },
      { "map": "Tiger Falls (Image 3)", "x": 3778, "y": 621 },
      { "map": "Tiger Falls (Image 3)", "x": 3823, "y": 621 }
    ]
  },
  {
    "name": "Tombstone Turretus Enemies",
    "sections": [ { "name": "Tombstone Turretus" } ],
    "map_locations": [
      { "map": "Robot Graveyard (Image 1)", "x": 1328, "y": 1909 },
      { "map": "Robot Graveyard (Image 1)", "x": 1494, "y": 1079 },
      { "map": "Robot Graveyard (Image 1)", "x": 1567, "y": 1390 },
      { "map": "Robot Graveyard (Image 1)", "x": 1826, "y": 1086 },
      { "map": "Robot Graveyard (Image 1)", "x": 1867, "y": 1797 },
      { "map": "Robot Graveyard (Image 1)", "x": 2041, "y": 1656 },
      { "map": "Robot Graveyard (Image 1)", "x": 2113, "y": 1976 },
      { "map": "Robot Graveyard (Image 1)", "x": 2148, "y": 1776 },
      { "map": "Robot Graveyard (Image 1)", "x": 2223, "y": 1016 },
      { "map": "Robot Graveyard (Image 1)", "x": 2707, "y": 1476 },
      { "map": "Robot Graveyard (Image 1)", "x": 2717, "y": 1893 },
      { "map": "Robot Graveyard (Image 1)", "x": 2733, "y": 1362 },
      { "map": "Robot Graveyard (Image 1)", "x": 2760, "y": 957 },
      { "map": "Robot Graveyard (Image 1)", "x": 3814, "y": 1209 },
      { "map": "Robot Graveyard (Image 2)", "x": 705, "y": 1711 },
      { "map": "Robot Graveyard (Image 2)", "x": 836, "y": 1369 },
      { "map": "Robot Graveyard (Image 2)", "x": 1308, "y": 1253 },
      { "map": "Robot Graveyard (Image 2)", "x": 1403, "y": 949 },
      { "map": "Robot Graveyard (Image 2)", "x": 2104, "y": 689 },
      { "map": "Robot Graveyard (Image 2)", "x": 2203, "y": 926 },
      { "map": "Robot Graveyard (Image 3)", "x": 334, "y": 1031 },
      { "map": "Robot Graveyard (Image 3)", "x": 493, "y": 1050 },
      { "map": "Robot Graveyard (Image 3)", "x": 541, "y": 1339 },
      { "map": "Robot Graveyard (Image 3)", "x": 1188, "y": 1428 },
      { "map": "Robot Graveyard (Image 3)", "x": 1454, "y": 1260 },
      { "map": "Robot Graveyard (Image 3)", "x": 1634, "y": 1235 }
    ]
  },
  {
    "name": "Zombie Trooper Enemies",
    "sections": [ { "name": "Zombie Trooper" } ],
    "map_locations": [
      { "map": "Robot Graveyard (Image 2)", "x": 675, "y": 1478 },
      { "map": "Robot Graveyard (Image 2)", "x": 793, "y": 1739 },
      { "map": "Robot Graveyard (Image 2)", "x": 895, "y": 1664 },
      { "map": "Robot Graveyard (Image 2)", "x": 1028, "y": 955 },
      { "map": "Robot Graveyard (Image 2)", "x": 1063, "y": 952 },
      { "map": "Robot Graveyard (Image 2)", "x": 1133, "y": 930 },
      { "map": "Robot Graveyard (Image 2)", "x": 1248, "y": 1638 },
      { "map": "Robot Graveyard (Image 2)", "x": 1449, "y": 1046 },
      { "map": "Robot Graveyard (Image 2)", "x": 1462, "y": 1044 },
      { "map": "Robot Graveyard (Image 2)", "x": 1664, "y": 950 },
      { "map": "Robot Graveyard (Image 2)", "x": 1804, "y": 1126 },
      { "map": "Robot Graveyard (Image 2)", "x": 1829, "y": 1128 },
      { "map": "Robot Graveyard (Image 2)", "x": 1905, "y": 1112 },
      { "map": "Robot Graveyard (Image 2)", "x": 2035, "y": 1114 },
      { "map": "Robot Graveyard (Image 2)", "x": 2169, "y": 952 },
      { "map": "Robot Graveyard (Image 2)", "x": 2628, "y": 1192 },
      { "map": "Robot Graveyard (Image 2)", "x": 2658, "y": 1088 },
      { "map": "Robot Graveyard (Image 2)", "x": 3024, "y": 871 },
      { "map": "Robot Graveyard (Image 2)", "x": 3078, "y": 851 },
      { "map": "Robot Graveyard (Image 2)", "x": 3112, "y": 846 },
      { "map": "Robot Graveyard (Image 2)", "x": 3156, "y": 762 },
      { "map": "Robot Graveyard (Image 2)", "x": 3208, "y": 840 },
      { "map": "Robot Graveyard (Image 3)", "x": 101, "y": 1145 },
      { "map": "Robot Graveyard (Image 3)", "x": 350, "y": 1027 },
      { "map": "Robot Graveyard (Image 3)", "x": 570, "y": 1047 },
      { "map": "Robot Graveyard (Image 3)", "x": 594, "y": 1054 },
      { "map": "Robot Graveyard (Image 3)", "x": 833, "y": 1015 },
      { "map": "Robot Graveyard (Image 3)", "x": 1866, "y": 1234 },
      { "map": "Robot Graveyard (Image 3)", "x": 1969, "y": 1234 },
      { "map": "Shade Armory (Image 1)", "x": 2027, "y": 1376 },
      { "map": "Shade Armory (Image 1)", "x": 2032, "y": 1549 },
      { "map": "Shade Armory (Image 1)", "x": 2062, "y": 1549 },
      { "map": "Shade Armory (Image 1)", "x": 2082, "y": 1778 },
      { "map": "Shade Armory (Image 1)", "x": 2186, "y": 1778 },
      { "map": "Shade Armory (Image 1)", "x": 2254, "y": 1742 },
      { "map": "Shade Armory (Image 1)", "x": 2297, "y": 1398 },
      { "map": "Shade Armory (Image 1)", "x": 2417, "y": 1402 },
      { "map": "Shade Armory (Image 2)", "x": 1802, "y": 1734 },
      { "map": "Shade Armory (Image 2)", "x": 2120, "y": 1734 }
    ]
  },
  {
    "name": "Troopish Enemies",
    "sections": [ { "name": "Troopish" } ],
    "map_locations": [
      { "map": "Shade Armory (Image 1)", "x": 1601, "y": 574 },
      { "map": "Shade Armory (Image 1)", "x": 1981, "y": 870 },
      { "map": "Shade Armory (Image 1)", "x": 2450, "y": 703 },
      { "map": "Shade Armory (Image 1)", "x": 2589, "y": 703 },
      { "map": "Shade Armory (Image 1)", "x": 3024, "y": 1511 },
      { "map": "Shade Armory (Image 1)", "x": 3325, "y": 946 },
      { "map": "Shade Armory (Image 2)", "x": 217, "y": 1681 },
      { "map": "Shade Armory (Image 2)", "x": 288, "y": 1784 },
      { "map": "Shade Armory (Image 2)", "x": 307, "y": 1784 },
      { "map": "Shade Armory (Image 2)", "x": 426, "y": 1767 },
      { "map": "Shade Armory (Image 2)", "x": 444, "y": 1392 },
      { "map": "Shade Armory (Image 2)", "x": 581, "y": 1272 },
      { "map": "Shade Armory (Image 2)", "x": 880, "y": 1485 },
      { "map": "Shade Armory (Image 2)", "x": 964, "y": 1775 },
      { "map": "Shade Armory (Image 2)", "x": 1035, "y": 1477 },
      { "map": "Shade Armory (Image 2)", "x": 1225, "y": 1630 },
      { "map": "Shade Armory (Image 2)", "x": 1357, "y": 1690 },
      { "map": "Shade Armory (Image 2)", "x": 2793, "y": 1049 },
      { "map": "Shade Armory (Image 2)", "x": 3090, "y": 640 },
      { "map": "Shade Armory (Image 2)", "x": 3124, "y": 743 }
    ]
  },
  {
    "name": "Sword Trooper Enemies",
    "sections": [ { "name": "Sword Trooper" } ],
    "map_locations": [
      { "map": "Shade Armory (Image 1)", "x": 1605, "y": 1387 },
      { "map": "Shade Armory (Image 1)", "x": 2307, "y": 1700 },
      { "map": "Shade Armory (Image 2)", "x": 3161, "y": 1355 },
      { "map": "Shade Armory (Image 2)", "x": 3329, "y": 1355 }
    ]
  },
  {
    "name": "Rifle Trooper Enemies",
    "sections": [ { "name": "Rifle Trooper" } ],
    "map_locations": [
      { "map": "Shade Armory (Image 1)", "x": 2400, "y": 1560 },
      { "map": "Shade Armory (Image 2)", "x": 2595, "y": 381 },
      { "map": "Shade Armory (Image 2)", "x": 2879, "y": 980 },
      { "map": "Shade Armory (Image 2)", "x": 3278, "y": 1355 }
    ]
  },
  {
    "name": "Wood Hopper Enemies",
    "sections": [ { "name": "Wood Hopper" } ],
    "map_locations": [
      { "map": "Avian Museum (Image 1)", "x": 1253, "y": 1668 },
      { "map": "Avian Museum (Image 1)", "x": 1815, "y": 1668 },
      { "map": "Avian Museum (Image 1)", "x": 3469, "y": 1162 },
      { "map": "Avian Museum (Image 2)", "x": 809, "y": 1535 },
      { "map": "Avian Museum (Image 2)", "x": 1106, "y": 1535 },
      { "map": "Avian Museum (Image 2)", "x": 3089, "y": 1563 },
      { "map": "Avian Museum (Image 5)", "x": 2605, "y": 1908 },
      { "map": "Avian Museum (Image 5)", "x": 2684, "y": 1908 },
      { "map": "Avian Museum (Image 5)", "x": 2764, "y": 1908 }
    ]
  },
  {
    "name": "Blast Cone Enemies",
    "sections": [ { "name": "Blast Cone" } ],
    "map_locations": [
      { "map": "Avian Museum (Image 1)", "x": 1665, "y": 1290 },
      { "map": "Avian Museum (Image 1)", "x": 1927, "y": 1406 },
      { "map": "Avian Museum (Image 1)", "x": 3107, "y": 1030 },
      { "map": "Avian Museum (Image 1)", "x": 3517, "y": 1177 },
      { "map": "Avian Museum (Image 1)", "x": 3620, "y": 1035 },
      { "map": "Avian Museum (Image 1)", "x": 3667, "y": 1607 },
      { "map": "Avian Museum (Image 2)", "x": 40, "y": 1557 },
      { "map": "Avian Museum (Image 2)", "x": 2093, "y": 1144 },
      { "map": "Avian Museum (Image 2)", "x": 3113, "y": 1277 },
      { "map": "Avian Museum (Image 3)", "x": 1120, "y": 1127 },
      { "map": "Avian Museum (Image 3)", "x": 1149, "y": 1347 },
      { "map": "Avian Museum (Image 4)", "x": 929, "y": 1300 },
      { "map": "Avian Museum (Image 4)", "x": 1496, "y": 1327 },
      { "map": "Avian Museum (Image 5)", "x": 379, "y": 1194 },
      { "map": "Avian Museum (Image 5)", "x": 1979, "y": 1744 },
      { "map": "Avian Museum (Image 5)", "x": 2139, "y": 1574 },
      { "map": "Avian Museum (Image 5)", "x": 2459, "y": 1574 },
      { "map": "Avian Museum (Image 5)", "x": 2965, "y": 1751 }
    ]
  },
  {
    "name": "Flamingo Enemies",
    "sections": [ { "name": "Flamingo" } ],
    "map_locations": [
      { "map": "Avian Museum (Image 1)", "x": 2221, "y": 1184 },
      { "map": "Avian Museum (Image 1)", "x": 2442, "y": 1130 },
      { "map": "Avian Museum (Image 2)", "x": 2155, "y": 1503 },
      { "map": "Avian Museum (Image 2)", "x": 2418, "y": 1060 },
      { "map": "Avian Museum (Image 2)", "x": 2622, "y": 1250 },
      { "map": "Avian Museum (Image 2)", "x": 3058, "y": 1060 },
      { "map": "Avian Museum (Image 3)", "x": 2915, "y": 1448 },
      { "map": "Avian Museum (Image 3)", "x": 2975, "y": 1300 },
      { "map": "Avian Museum (Image 3)", "x": 2988, "y": 1380 },
      { "map": "Avian Museum (Image 4)", "x": 3711, "y": 1822 },
      { "map": "Avian Museum (Image 5)", "x": 1477, "y": 1463 }
    ]
  },
  {
    "name": "Cocoon Enemies",
    "sections": [ { "name": "Cocoon" } ],
    "map_locations": [
      { "map": "Avian Museum (Image 1)", "x": 3102, "y": 1183 },
      { "map": "Avian Museum (Image 1)", "x": 3406, "y": 1209 },
      { "map": "Avian Museum (Image 1)", "x": 3522, "y": 1235 },
      { "map": "Avian Museum (Image 1)", "x": 3795, "y": 1422 },
      { "map": "Avian Museum (Image 4)", "x": 1561, "y": 970 }
    ]
  },
  {
    "name": "Torcher Enemies",
    "sections": [ { "name": "Torcher" } ],
    "map_locations": [
      { "map": "Avian Museum (Image 2)", "x": 1875, "y": 1467 },
      { "map": "Avian Museum (Image 2)", "x": 3407, "y": 1121 },
      { "map": "Avian Museum (Image 2)", "x": 3644, "y": 1211 },
      { "map": "Avian Museum (Image 3)", "x": 195, "y": 1549 },
      { "map": "Avian Museum (Image 3)", "x": 1075, "y": 1087 },
      { "map": "Avian Museum (Image 5)", "x": 381, "y": 1580 }
    ]
  },
  {
    "name": "Macer Enemies",
    "sections": [ { "name": "Macer" } ],
    "map_locations": [
      { "map": "Avian Museum (Image 2)", "x": 2964, "y": 1529 },
      { "map": "Avian Museum (Image 3)", "x": 1020, "y": 1369 },
      { "map": "Avian Museum (Image 4)", "x": 1475, "y": 1051 },
      { "map": "Avian Museum (Image 4)", "x": 1716, "y": 1194 },
      { "map": "Avian Museum (Image 4)", "x": 2649, "y": 1104 },
      { "map": "Avian Museum (Image 4)", "x": 3716, "y": 1251 },
      { "map": "Avian Museum (Image 5)", "x": 402, "y": 1478 },
      { "map": "Avian Museum (Image 5)", "x": 769, "y": 1797 }
    ]
  },
  {
    "name": "Mantis Enemies",
    "sections": [ { "name": "Mantis" } ],
    "map_locations": [
      { "map": "Airship Sigwada (Image 1)", "x": 921, "y": 1941 },
      { "map": "Airship Sigwada (Image 1)", "x": 1241, "y": 1854 },
      { "map": "Airship Sigwada (Image 1)", "x": 1241, "y": 1992 },
      { "map": "Airship Sigwada (Image 2)", "x": 287, "y": 1173 },
      { "map": "Airship Sigwada (Image 2)", "x": 513, "y": 1273 },
      { "map": "Airship Sigwada (Image 2)", "x": 1699, "y": 1029 },
      { "map": "Airship Sigwada (Image 2)", "x": 1919, "y": 1129 },
      { "map": "Airship Sigwada (Image 2)", "x": 4577, "y": 1583 },
      { "map": "Airship Sigwada (Image 3)", "x": 901, "y": 159 },
      { "map": "Airship Sigwada (Image 5)", "x": 2887, "y": 1159 },
      { "map": "Airship Sigwada (Image 6)", "x": 181, "y": 1159 },
      { "map": "Airship Sigwada (Image 6)", "x": 715, "y": 1072 },
      { "map": "Airship Sigwada (Image 6)", "x": 2167, "y": 1263 },
      { "map": "Airship Sigwada (Image 6)", "x": 2248, "y": 1246 },
      { "map": "Airship Sigwada (Image 6)", "x": 2332, "y": 1263 }
    ]
  },
  {
    "name": "Flash Mouth Enemies",
    "sections": [ { "name": "Flash Mouth" } ],
    "map_locations": [
      { "map": "Airship Sigwada (Image 1)", "x": 1118, "y": 1864 },
      { "map": "Airship Sigwada (Image 2)", "x": 4328, "y": 1104 },
      { "map": "Airship Sigwada (Image 2)", "x": 4562, "y": 1126 },
      { "map": "Airship Sigwada (Image 5)", "x": 2390, "y": 1240 },
      { "map": "Airship Sigwada (Image 6)", "x": 1045, "y": 1196 },
      { "map": "Airship Sigwada (Image 6)", "x": 1161, "y": 1124 },
      { "map": "Airship Sigwada (Image 6)", "x": 1387, "y": 1296 },
      { "map": "Airship Sigwada (Image 6)", "x": 1401, "y": 1196 },
      { "map": "Airship Sigwada (Image 6)", "x": 2211, "y": 977 },
      { "map": "Airship Sigwada (Image 6)", "x": 2245, "y": 1082 }
    ]
  },
  {
    "name": "Girder Enemies",
    "sections": [ { "name": "Girder" } ],
    "map_locations": [
      { "map": "Airship Sigwada (Image 2)", "x": 1345, "y": 1174 },
      { "map": "Airship Sigwada (Image 2)", "x": 1648, "y": 1428 },
      { "map": "Airship Sigwada (Image 2)", "x": 3742, "y": 1653 },
      { "map": "Airship Sigwada (Image 2)", "x": 4487, "y": 1428 },
      { "map": "Airship Sigwada (Image 2)", "x": 5041, "y": 1678 },
      { "map": "Airship Sigwada (Image 5)", "x": 1852, "y": 1268 },
      { "map": "Airship Sigwada (Image 5)", "x": 1914, "y": 1268 },
      { "map": "Airship Sigwada (Image 5)", "x": 1976, "y": 1268 },
      { "map": "Airship Sigwada (Image 6)", "x": 974, "y": 1409 },
      { "map": "Airship Sigwada (Image 6)", "x": 1196, "y": 1390 },
      { "map": "Airship Sigwada (Image 6)", "x": 1280, "y": 1361 }
    ]
  }
]